reki/__init__.py
reki/_util.py
reki/_version.py
reki/data_finder/README.md
reki/data_finder/__init__.py
reki/data_finder/__main__.py
reki/data_finder/_config.py
reki/data_finder/_util.py
reki/data_finder/local.py
reki/data_finder/conf/cm/glob/gfs/grib2/0p50.yaml
reki/data_finder/conf/cm/glob/gfs/grib2/1p00.yaml
reki/data_finder/conf/cmadaas/cma_geps/grib2/orig.yaml
reki/data_finder/conf/cmadaas/cma_gfs/grib2/orig.yaml
reki/data_finder/conf/cmadaas/cma_meso/grib2/orig.yaml
reki/data_finder/conf/cmadaas/cma_reps/grib2/orig.yaml
reki/data_finder/conf/cmadaas/cma_tym/grib2/orig.yaml
reki/data_finder/conf/od/cma_geps/grib2/orig.yaml
reki/data_finder/conf/od/cma_gfs_gmf/bin/modelvar.yaml
reki/data_finder/conf/od/cma_gfs_gmf/bin/modelvar_ctl.yaml
reki/data_finder/conf/od/cma_gfs_gmf/bin/postvar.yaml
reki/data_finder/conf/od/cma_gfs_gmf/bin/postvar_ctl.yaml
reki/data_finder/conf/od/cma_gfs_gmf/grib2/modelvar.yaml
reki/data_finder/conf/od/cma_gfs_gmf/grib2/ne.yaml
reki/data_finder/conf/od/cma_gfs_gmf/grib2/orig.yaml
reki/data_finder/conf/od/cma_gfs_gmf/obs/r2cwe.yaml
reki/data_finder/conf/od/cma_gfs_gmf/obs/rgwst.yaml
reki/data_finder/conf/od/cma_gfs_gmf/obs/rsing.yaml
reki/data_finder/conf/od/cma_gfs_gmf/obs/rsurf.yaml
reki/data_finder/conf/od/cma_gfs_gmf/obs/rtemp.yaml
reki/data_finder/conf/od/cma_meso_1km/grib2/modelvar.yaml
reki/data_finder/conf/od/cma_meso_1km/grib2/orig.yaml
reki/data_finder/conf/od/cma_meso_3km/bin/modelvar.yaml
reki/data_finder/conf/od/cma_meso_3km/bin/modelvar_ctl.yaml
reki/data_finder/conf/od/cma_meso_3km/bin/postvar.yaml
reki/data_finder/conf/od/cma_meso_3km/bin/postvar_ctl.yaml
reki/data_finder/conf/od/cma_meso_3km/grib2/modelvar.yaml
reki/data_finder/conf/od/cma_meso_3km/grib2/orig.yaml
reki/data_finder/conf/od/cma_reps/grib2/orig.yaml
reki/data_finder/conf/od/cma_tym/bin/postvar.yaml
reki/data_finder/conf/od/cma_tym/bin/postvar_ctl.yaml
reki/data_finder/conf/od/cma_tym/grib2/modelvar.yaml
reki/data_finder/conf/od/cma_tym/grib2/orig.yaml
reki-2025.7.2.dist-info/licenses/LICENSE
reki-2025.7.2.dist-info/METADATA
reki-2025.7.2.dist-info/WHEEL
reki-2025.7.2.dist-info/top_level.txt
reki-2025.7.2.dist-info/RECORD
