Metadata-Version: 2.4
Name: reki
Version: 2025.7.2
Summary: A data preparation tool for CEMC/CMA.
Author-email: Wang Dapeng <perillaroc@gmail.com>
License: 
Project-URL: Homepage, https://github.com/cemc-oper/reki
Project-URL: Documentation, https://reki.readthedocs.io
Project-URL: Repository, https://github.com/cemc-oper/reki.git
Keywords: data,grib2,cemc
Classifier: Development Status :: 4 - Beta
Classifier: Intended Audience :: Developers
Classifier: License :: OSI Approved :: Apache Software License
Classifier: Programming Language :: Python :: 3.11
Classifier: Programming Language :: Python :: 3.12
License-File: LICENSE
Requires-Dist: pyyaml
Requires-Dist: jinja2
Requires-Dist: numpy
Requires-Dist: pandas
Requires-Dist: xarray
Requires-Dist: click
Requires-Dist: tqdm
Requires-Dist: importlib-metadata; python_version < "3.8"
Provides-Extra: grib2
Requires-Dist: cfgrib; extra == "grib2"
Requires-Dist: eccodes; extra == "grib2"
Provides-Extra: godas
Requires-Dist: protobuf; extra == "godas"
Requires-Dist: requests; extra == "godas"
Provides-Extra: test
Requires-Dist: pytest; extra == "test"
Requires-Dist: requests; extra == "test"
Provides-Extra: cov
Requires-Dist: pytest-cov; extra == "cov"
Requires-Dist: codecov; extra == "cov"
Dynamic: license-file
